[
    {
        "dutch": "de katapult (-en)",
        "english": "the catapult (-s)",
        "vietnamese": "máy ném đá (-s)",
        "dutchsentence": "De jongen speelde met zijn katapult in het bos.",
        "englishtranslate": "The boy played with his catapult in the forest."
    },
    {
        "dutch": "het nieuws",
        "english": "the news",
        "vietnamese": "tin tức",
        "dutchsentence": "Heb je het nieuws van vanochtend al gelezen?",
        "englishtranslate": "Have you read the news from this morning yet?"
    },
    {
        "dutch": "de krant (-en)",
        "english": "the newspaper (-s)",
        "vietnamese": "báo (-s)",
        "dutchsentence": "Ik koop elke dag de krant bij de kiosk.",
        "englishtranslate": "I buy the newspaper at the kiosk every day."
    },
    {
        "dutch": "het kantoor (kantoren)",
        "english": "the office (-s)",
        "vietnamese": "văn phòng (-s)",
        "dutchsentence": "Mijn kantoor is op de vierde verdieping.",
        "englishtranslate": "My office is on the fourth floor."
    },
    {
        "dutch": "recht",
        "english": "straight",
        "vietnamese": "thẳng",
        "dutchsentence": "Trek een rechte lijn met een liniaal.",
        "englishtranslate": "Draw a straight line with a ruler."
    },
    {
        "dutch": "scheef",
        "english": "crooked",
        "vietnamese": "xiên",
        "dutchsentence": "Het schilderij hangt een beetje scheef.",
        "englishtranslate": "The painting is hanging a little crooked."
    },
    {
        "dutch": "terwijl",
        "english": "while",
        "vietnamese": "trong khi",
        "dutchsentence": "Ik luisterde naar de radio, terwijl ik werkte.",
        "englishtranslate": "I listened to the radio while I worked."
    },
    {
        "dutch": "toen",
        "english": "when",
        "vietnamese": "khi",
        "dutchsentence": "Toen ik klein was, woonde ik in Duitsland.",
        "englishtranslate": "When I was little, I lived in Germany."
    },
    {
        "dutch": "zitten",
        "english": "to sit",
        "vietnamese": "ngồi",
        "dutchsentence": "Zit op de stoel, alsjeblieft.",
        "englishtranslate": "Sit on the chair, please."
    }
]