[
    {"dutch": "het tussenwoord (-en)", "english": "the interjection(s)", "vietnamese": "thán từ"},
    {"dutch": "het feit (-en)", "english": "the fact(s)", "vietnamese": "sự thật"},
    {"dutch": "de hemel", "english": "the heaven", "vietnamese": "thiên đường"},
    {"dutch": "de hel", "english": "the hell", "vietnamese": "địa ngục"},
    {"dutch": "God", "english": "God", "vietnamese": "Chúa"},
    {"dutch": "Jezus", "english": "Jesus", "vietnamese": "Giêsu"},
    {"dutch": "Katholiek", "english": "Catholic", "vietnamese": "Công giáo"},
    {"dutch": "Protestants", "english": "Protestant", "vietnamese": "Tin lành"},
    {"dutch": "toe", "english": "to", "vietnamese": "đến"},
    {"dutch": "eigenlijk", "english": "actually", "vietnamese": "thực ra"},
    {"dutch": "in feite", "english": "in fact", "vietnamese": "thực tế"},
    {"dutch": "nietwaar", "english": "isn't it", "vietnamese": "phải không"},
    {"dutch": "afgelopen", "english": "finished", "vietnamese": "kết thúc"},
    {"dutch": "geloven, geloofd", "english": "(to) believe, believed", "vietnamese": "(để) tin, đã tin"},
    {"dutch": "beloven, beloofd", "english": "(to) promise, promised", "vietnamese": "(để) hứa, đã hứa"}
]