[
    {"dutch": "het spel (-len)", "english": "the game (games)", "vietnamese": "trò chơi (những trò chơi)"},
    {"dutch": "scheidbaar", "english": "separable", "vietnamese": "có thể tách rời"},
    {"dutch": "zelf", "english": "self", "vietnamese": "bản thân"},
    {"dutch": "binnenkomen (binnengekomen)", "english": "to enter (entered)", "vietnamese": "vào (đã vào)"},
    {"dutch": "opgeven (opgegeven)", "english": "to give up (given up)", "vietnamese": "bỏ cuộc (đã bỏ cuộc)"},
    {"dutch": "krijgen", "english": "to get", "vietnamese": "nhận"},
    {"dutch": "kijken", "english": "to look", "vietnamese": "nhìn"},
    {"dutch": "rijden", "english": "to drive", "vietnamese": "lái xe"},
    {"dutch": "blijven", "english": "to stay", "vietnamese": "ở lại"},
    {"dutch": "beschrijven", "english": "to describe", "vietnamese": "mô tả"},
    {"dutch": "bewijzen", "english": "to prove", "vietnamese": "chứng minh"},
    {"dutch": "lijken", "english": "to seem", "vietnamese": "dường như"},
    {"dutch": "houden", "english": "to hold", "vietnamese": "giữ"},
    {"dutch": "helpen", "english": "to help", "vietnamese": "giúp đỡ"},
    {"dutch": "vallen", "english": "to fall", "vietnamese": "ngã"},
    {"dutch": "laten", "english": "to let", "vietnamese": "để"},
    {"dutch": "lopen", "english": "to walk", "vietnamese": "đi bộ"},
    {"dutch": "slapen", "english": "to sleep", "vietnamese": "ngủ"},
    {"dutch": "sterven", "english": "to die", "vietnamese": "chết"},
    {"dutch": "worden", "english": "to become", "vietnamese": "trở thành"},
    {"dutch": "vriezen", "english": "to freeze", "vietnamese": "đóng băng"}
  ]